helloworld.py
helloworld_vk-0.0.1.dist-info/LICENSE.txt
helloworld_vk-0.0.1.dist-info/METADATA
helloworld_vk-0.0.1.dist-info/WHEEL
helloworld_vk-0.0.1.dist-info/top_level.txt
helloworld_vk-0.0.1.dist-info/RECORD
